deltarescdk/__init__.py
deltarescdk/kube_bucket.py
deltarescdk/utils.py
deltarescdk-0.1.1.dist-info/LICENSE
deltarescdk-0.1.1.dist-info/METADATA
deltarescdk-0.1.1.dist-info/WHEEL
deltarescdk-0.1.1.dist-info/top_level.txt
deltarescdk-0.1.1.dist-info/RECORD
