Metadata-Version: 2.1
Name: deltarescdk
Version: 0.1.1
Summary: cdk contructs for Deltares Infrastructure
Author: Jaap Langemeijer
License: UNKNOWN
Platform: UNKNOWN
Classifier: Development Status :: 4 - Beta
Classifier: Intended Audience :: Developers
Classifier: Programming Language :: JavaScript
Classifier: Programming Language :: Python :: 3 :: Only
Classifier: Programming Language :: Python :: 3.6
Classifier: Programming Language :: Python :: 3.7
Classifier: Programming Language :: Python :: 3.8
Classifier: Topic :: Software Development :: Code Generators
Classifier: Topic :: Utilities
Classifier: Typing :: Typed
Requires-Python: >=3.6
License-File: LICENSE
Requires-Dist: aws-cdk.core (==1.128.0)
Requires-Dist: aws-cdk.aws-s3 (==1.128.0)
Requires-Dist: aws-cdk.aws-ec2 (==1.128.0)
Requires-Dist: boto3 (==1.20.20)
